LICENSE
MANIFEST.in
README.md
setup.cfg
setup.py
django_improved_permissions.egg-info/PKG-INFO
django_improved_permissions.egg-info/SOURCES.txt
django_improved_permissions.egg-info/dependency_links.txt
django_improved_permissions.egg-info/top_level.txt
improved_permissions/__init__.py
improved_permissions/admin.py
improved_permissions/apps.py
improved_permissions/assignments.py
improved_permissions/checkers.py
improved_permissions/exceptions.py
improved_permissions/getters.py
improved_permissions/mixins.py
improved_permissions/models.py
improved_permissions/roles.py
improved_permissions/shortcuts.py
improved_permissions/utils.py
improved_permissions/migrations/0001_initial.py
improved_permissions/migrations/0002_auto_20180227_2108.py
improved_permissions/migrations/__init__.py
improved_permissions/templatetags/__init__.py
improved_permissions/templatetags/roletags.py