Metadata-Version: 1.1
Name: django-improved-permissions
Version: 0.1.4
Summary: A Django app to handle all kinds of permissions and roles.
Home-page: https://github.com/s-sys/django-improved-permissions
Author: S-SYS Sistemas e Soluções Tecnológicas
Author-email: contato@ssys.com.br
License: MIT License
Platform: UNKNOWN
Classifier: Environment :: Web Environment
Classifier: Framework :: Django
Classifier: Framework :: Django :: 2.0
Classifier: Intended Audience :: Developers
Classifier: Programming Language :: Python
Classifier: Programming Language :: Python :: 3.6
